moban_haml/__init__.py
moban_haml/_version.py
moban_haml/engine.py
moban_haml-0.0.1.dist-info/LICENSE
moban_haml-0.0.1.dist-info/METADATA
moban_haml-0.0.1.dist-info/WHEEL
moban_haml-0.0.1.dist-info/top_level.txt
moban_haml-0.0.1.dist-info/RECORD
